setup.py
twinkle/__init__.py
twinkle.egg-info/PKG-INFO
twinkle.egg-info/SOURCES.txt
twinkle.egg-info/dependency_links.txt
twinkle.egg-info/requires.txt
twinkle.egg-info/top_level.txt