Metadata-Version: 1.1
Name: twinkle
Version: 0.0.5
Summary: Twinkle - Twitter Analysis Toolkit
Home-page: https://github.com/emCOMP/twinkle
Author: emComp Lab
Author-email: emcomp@uw.edu
License: MIT
Download-URL: https://github.com/emCOMP/twinkle/tarball/0.0.5
Platform: any
Classifier: Development Status :: 3 - Alpha
Classifier: Environment :: Console
Classifier: Intended Audience :: Developers
Classifier: Natural Language :: English
Classifier: License :: OSI Approved :: MIT License
Classifier: Programming Language :: Python
Classifier: Programming Language :: Python :: 2
Classifier: Programming Language :: Python :: 2.7
Classifier: Topic :: Software Development :: Libraries
